CONTRIBUTORS
LICENSE
MANIFEST.in
README.rst
setup.py
cmsplugin_text_ng/__init__.py
cmsplugin_text_ng/admin.py
cmsplugin_text_ng/cms_plugins.py
cmsplugin_text_ng/compat.py
cmsplugin_text_ng/exceptions.py
cmsplugin_text_ng/forms.py
cmsplugin_text_ng/models.py
cmsplugin_text_ng/type_registry.py
cmsplugin_text_ng/utils.py
cmsplugin_text_ng.egg-info/PKG-INFO
cmsplugin_text_ng.egg-info/SOURCES.txt
cmsplugin_text_ng.egg-info/dependency_links.txt
cmsplugin_text_ng.egg-info/not-zip-safe
cmsplugin_text_ng.egg-info/requires.txt
cmsplugin_text_ng.egg-info/top_level.txt
cmsplugin_text_ng/contrib/__init__.py
cmsplugin_text_ng/contrib/textng_filer/__init__.py
cmsplugin_text_ng/contrib/textng_filer/models.py
cmsplugin_text_ng/contrib/textng_filer/migrations/0001_initial.py
cmsplugin_text_ng/contrib/textng_filer/migrations/__init__.py
cmsplugin_text_ng/migrations/0001_initial.py
cmsplugin_text_ng/migrations/0002_auto__add_textngvariabletext__add_unique_textngvariabletext_text_ng_la.py
cmsplugin_text_ng/migrations/__init__.py
cmsplugin_text_ng/templatetags/__init__.py
cmsplugin_text_ng/templatetags/text_ng_tags.py