Metadata-Version: 1.1
Name: cmsplugin-text-ng
Version: 0.4
Summary: django-cms improved text plugin
Home-page: https://github.com/KristianOellegaard/cmsplugin-text-ng
Author: Kristian Øllegaard, Benjamin Wohlwend
Author-email: kristian@oellegaard.com
License: UNKNOWN
Platform: UNKNOWN
Classifier: Development Status :: 3 - Alpha
Classifier: Framework :: Django
Classifier: Intended Audience :: Developers
Classifier: License :: OSI Approved :: BSD License
Classifier: Operating System :: OS Independent
Classifier: Programming Language :: Python :: 2.6
Classifier: Programming Language :: Python :: 2.7
Classifier: Topic :: Internet :: WWW/HTTP :: Dynamic Content
